llama_index/node_parser/relational/dashscope/__init__.py
llama_index/node_parser/relational/dashscope/base.py
llama_index_node_parser_relational_dashscope-0.1.0.dist-info/METADATA
llama_index_node_parser_relational_dashscope-0.1.0.dist-info/WHEEL
llama_index_node_parser_relational_dashscope-0.1.0.dist-info/RECORD
